dotmap/__init__.py
dotmap/test.py
dotmap-1.3.30.dist-info/LICENSE.txt
dotmap-1.3.30.dist-info/METADATA
dotmap-1.3.30.dist-info/WHEEL
dotmap-1.3.30.dist-info/top_level.txt
dotmap-1.3.30.dist-info/RECORD
