Metadata-Version: 2.1
Name: dotmap
Version: 1.3.30
Summary: ordered, dynamically-expandable dot-access dictionary
Home-page: https://github.com/drgrib/dotmap
Author: Chris Redford
Author-email: credford@gmail.com
License: MIT
Download-URL: https://github.com/drgrib/dotmap/tarball/1.0
Keywords: dict,dot,map,order,ordered,ordereddict,access,dynamic
Platform: UNKNOWN
